{
    "ADMIN_FOLDER": "ADMIN",
    "COMPRESSED": false,
    "COMPRESSED_DATE": "",
    "COMPRESSED_STAMP": 0,
    "CURRENCY_ISO": "USD",
    "DEF_ARR_SIZES": {
        "min": 400,
        "max": 800
    },
    "DISPLAY_PRODUCTS": "mozaic",
    "DO_COMPRESS_JS_CSS": false,
    "HOST": "my-shop.com",
    "LANG_BACK": "en",
    "LANG_FRONT": "en",
    "LANG_LOCALE": "en_US",
    "LAST_UPDATE": "Wednesday, February 8, 2023 at 6:23 PM",
    "LOGO": "logo-shop-alhnzivtfyqrcswogebdxmukpj-0-1670200102.png",
    "LOGO_SN": "logo-sn-mzposnfgwqalrvxuicdtbykhje-0-1675869781.png",
    "LOGO_SN_SIZE": 900,
    "META_DESCR": "Placido-Shop Online Sale Software",
    "NB_FOR_PAGINA": 4,
    "NB_FOR_PAGINA_BACKEND": 4,
    "PUBLIC_NOTIFICATION_MAIL": "user@placido-shop.com",
    "SHORT_TEXT": 300,
    "SLIDER": {
        "display": true,
        "play": false,
        "delay": 3000,
        "speed": 2000
    },
    "TIMEZONE": "America\/Los_Angeles",
    "TOKEN_TIME": 3600,
    "VERSION": "2.2.3",
    "WEBSITE_TITLE": "Placido-Shop"
}